{
  "id": 100000051,
  "name": "Dragoon\u0027s Circle",
  "is_illegal": false,
  "is_custom": true,
  "text": "This card is always treated as an \"Omni\" Spell. When this card is activated, you can send up to 3 \"Dragoon\" monsters with different names from your Extra Deck to the GY. When an Omni monster is Summoned: Target 1 card the opponent controls; destroy it. You can only use each effect of \"Dragoon\u0027s Circle\" once per turn.",
  "images": [
    "https://www.dropbox.com/scl/fi/p1c3s16yj1issq32m7eyx/100000051.jpeg?rlkey=08xpkk7qj53jjfttm8xgg4fxy\u0026st=6o3y1q8f\u0026dl=1"
  ],
  "type": "Spell",
  "spell_type": "Continuous"
}
